memvid/__init__.py
memvid/chat.py
memvid/config.py
memvid/encoder.py
memvid/index.py
memvid/interactive.py
memvid/retriever.py
memvid/utils.py
memvid-0.1.1.dist-info/licenses/LICENSE
tests/__init__.py
tests/test_encoder.py
tests/test_retriever.py
tests/test_utils.py
memvid-0.1.1.dist-info/METADATA
memvid-0.1.1.dist-info/WHEEL
memvid-0.1.1.dist-info/top_level.txt
memvid-0.1.1.dist-info/RECORD
